[{"f":"documents\\2021\\spanish-grand-prix\\transcripts\\friday.md","t":"Friday Transcript","n":1},{"f":"documents\\2021\\spanish-grand-prix\\transcripts\\saturday.md","t":"Saturday Transcript","n":1},{"f":"documents\\2021\\spanish-grand-prix\\circuit-map.pdf","t":"Circuit Map","n":1,"p":"05.05.21 09:50"},{"f":"documents\\2021\\spanish-grand-prix\\transcripts\\friday.md","t":"Friday Press Conference Transcript","n":2},{"f":"documents\\2021\\spanish-grand-prix\\transcripts\\sunday.md","t":"Sunday Transcript","n":2},{"f":"documents\\2021\\spanish-grand-prix\\2021-portuguese-grand-prix-post-race-inspections-on-car-number-04.pdf","t":"2021 Portuguese Grand Prix Post Race Inspections on Car Number 04","n":2,"p":"05.05.21 15:12"},{"f":"documents\\2021\\spanish-grand-prix\\pu-elements-used-per-driver-up-to-now.pdf","t":"PU elements used per driver up to now","n":3,"p":"06.05.21 11:32"},{"f":"documents\\2021\\spanish-grand-prix\\race-directors-event-notes.pdf","t":"Race Directors' Event Notes","n":4,"p":"06.05.21 11:51"},{"f":"documents\\2021\\spanish-grand-prix\\race-directors-event-notes-version-2.pdf","t":"Race Directors' Event Notes Version 2","n":5,"p":"06.05.21 13:49"},{"f":"documents\\2021\\spanish-grand-prix\\initial-scrutineering.pdf","t":"Initial Scrutineering","n":6,"p":"06.05.21 16:48"},{"f":"documents\\2021\\spanish-grand-prix\\entry-list.pdf","t":"Entry List","n":7,"p":"06.05.21 17:05"},{"f":"documents\\2021\\spanish-grand-prix\\p1-deleted-lap-times-turn-2.pdf","t":"P1 deleted lap times turn 2","n":8,"p":"07.05.21 12:38"},{"f":"documents\\2021\\spanish-grand-prix\\p1-classification.pdf","t":"P1 Classification","n":9,"p":"07.05.21 12:45"},{"f":"documents\\2021\\spanish-grand-prix\\p2-classification.pdf","t":"P2 Classification","n":10,"p":"07.05.21 16:15"},{"f":"documents\\2021\\spanish-grand-prix\\race-directors-note-sc1-sc2-time.pdf","t":"Race Directors' Note SC1-SC2 Time","n":11,"p":"07.05.21 16:29"},{"f":"documents\\2021\\spanish-grand-prix\\race-directors-note-p3-tyres.pdf","t":"Race Directors' Note - P3 Tyres","n":12,"p":"07.05.21 16:42"},{"f":"documents\\2021\\spanish-grand-prix\\p1-and-p2-scrutineering.pdf","t":"P1 and P2 scrutineering","n":13,"p":"07.05.21 18:48"},{"f":"documents\\2021\\spanish-grand-prix\\new-gearboxes-for-this-event.pdf","t":"New gearboxes for this Event","n":14,"p":"07.05.21 18:51"},{"f":"documents\\2021\\spanish-grand-prix\\new-pu-elements-for-this-event.pdf","t":"New PU elements for this Event","n":15,"p":"08.05.21 12:19"},{"f":"documents\\2021\\spanish-grand-prix\\race-directors-note-post-qualifying-procedure.pdf","t":"Race Directors Note - Post Qualifying Procedure","n":16,"p":"08.05.21 13:09"},{"f":"documents\\2021\\spanish-grand-prix\\p3-classification.pdf","t":"P3 Classification","n":17,"p":"08.05.21 13:15"},{"f":"documents\\2021\\spanish-grand-prix\\summons-car-4-turn-14-incident-with-car-9.pdf","t":"Summons - Car 4 - Turn 14 incident with car 9","n":18,"p":"08.05.21 16:26"},{"f":"documents\\2021\\spanish-grand-prix\\summons-car-9-turn-14-incident-with-car-4.pdf","t":"Summons - Car 9 - Turn 14 incident with car 4","n":19,"p":"08.05.21 16:26"},{"f":"documents\\2021\\spanish-grand-prix\\provisional-qualifying-classification.pdf","t":"Provisional Qualifying Classification","n":20,"p":"08.05.21 16:35"},{"f":"documents\\2021\\spanish-grand-prix\\offence-car-9-impeding-car-4-in-turn-14.pdf","t":"Offence - Car 9 - impeding car 4 in turn 14","n":21,"p":"08.05.21 18:17"},{"f":"documents\\2021\\spanish-grand-prix\\dry-tyre-type-used-during-fastest-lap-in-q2.pdf","t":"Dry tyre type used during fastest lap in Q2","n":22,"p":"08.05.21 19:10"},{"f":"documents\\2021\\spanish-grand-prix\\p3-and-qualifying-scrutineering.pdf","t":"P3 and Qualifying scrutineering","n":23,"p":"08.05.21 19:38"},{"f":"documents\\2021\\spanish-grand-prix\\final-qualifying-classification.pdf","t":"Final Qualifying Classification","n":24,"p":"08.05.21 19:45"},{"f":"documents\\2021\\spanish-grand-prix\\provisional-starting-grid.pdf","t":"Provisional Starting Grid","n":25,"p":"08.05.21 19:47"},{"f":"documents\\2021\\spanish-grand-prix\\race-directors-note-pre-race-procedure.pdf","t":"Race Directors Note - Pre-Race Procedure","n":26,"p":"09.05.21 13:01"},{"f":"documents\\2021\\spanish-grand-prix\\race-directors-note-post-race-procedure.pdf","t":"Race Directors Note - Post Race Procedure","n":27,"p":"09.05.21 13:02"},{"f":"documents\\2021\\spanish-grand-prix\\parts-and-parameters-been-replaced-or-changed-during-the-parc-ferm\u00e9.pdf","t":"Parts and parameters been replaced or changed during the Parc Ferm\u00e9","n":28,"p":"09.05.21 13:56"},{"f":"documents\\2021\\spanish-grand-prix\\final-starting-grid.pdf","t":"Final Starting Grid","n":29,"p":"09.05.21 14:00"},{"f":"documents\\2021\\spanish-grand-prix\\offence-car-10-out-of-position-at-race-start.pdf","t":"Offence - Car 10 - out of position at race start","n":30,"p":"09.05.21 16:52"},{"f":"documents\\2021\\spanish-grand-prix\\summons-car-14-turn-2-incident-with-car-18.pdf","t":"Summons - Car 14 - Turn 2 incident with car 18","n":31,"p":"09.05.21 16:53"},{"f":"documents\\2021\\spanish-grand-prix\\summons-car-18-turn-2-incident-with-car-14.pdf","t":"Summons - Car 18 - Turn 2 incident with car 14","n":32,"p":"09.05.21 16:53"},{"f":"documents\\2021\\spanish-grand-prix\\race-deleted-lap-times-turn-2.pdf","t":"Race deleted lap times turn 2","n":33,"p":"09.05.21 17:02"},{"f":"documents\\2021\\spanish-grand-prix\\provisional-race-classification.pdf","t":"Provisional Race Classification","n":34,"p":"09.05.21 17:06"},{"f":"documents\\2021\\spanish-grand-prix\\decision-car-14-turn-2-incident-with-car-18.pdf","t":"Decision - Car 14 - Turn 2 Incident with car 18","n":35,"p":"09.05.21 18:12"},{"f":"documents\\2021\\spanish-grand-prix\\decision-car-18-turn-2-incident-with-car-14.pdf","t":"Decision - Car 18 - Turn 2 incident with car 14","n":36,"p":"09.05.21 18:12"},{"f":"documents\\2021\\spanish-grand-prix\\race-scrutineering.pdf","t":"Race scrutineering","n":37,"p":"09.05.21 19:11"},{"f":"documents\\2021\\spanish-grand-prix\\final-race-classification.pdf","t":"Final Race Classification","n":38,"p":"09.05.21 19:31"},{"f":"documents\\2021\\spanish-grand-prix\\championship-points.pdf","t":"Championship Points","n":39,"p":"09.05.21 19:35"}]