[{"f":"event-notes-pirelli-preview.pdf","t":"Event Notes - Pirelli Preview","n":1,"p":"22.05.24 12:51"},{"f":"post-race-checks-on-car-16-emilia-romagna-gp.pdf","t":"Post-Race Checks on Car 16, Emilia Romagna GP","n":2,"p":"22.05.24 16:01"},{"f":"race-directors-event-notes.pdf","t":"Race Director's Event Notes","n":3,"p":"22.05.24 16:02"},{"f":"event-notes-circuit-map-pit-lane-drawing-and-red-zone.pdf","t":"Event Notes - Circuit Map, Pit Lane Drawing and Red Zone","n":4,"p":"23.05.24 15:19"},{"f":"car-display-procedure.pdf","t":"Car Display Procedure","n":5,"p":"23.05.24 18:16"},{"f":"pu-elements-used-per-driver-up-to-now.pdf","t":"PU elements used per driver up to now","n":6,"p":"24.05.24 09:33"},{"f":"rncs-used-per-driver-up-to-now.pdf","t":"RNCs used per driver up to now","n":7,"p":"24.05.24 09:33"},{"f":"car-presentation-submissions.pdf","t":"Car Presentation Submissions","n":8,"p":"24.05.24 11:00"},{"f":"self-scrutineering.pdf","t":"Self Scrutineering","n":9,"p":"24.05.24 11:17"},{"f":"entry-list.pdf","t":"Entry List","n":10,"p":"24.05.24 11:30"},{"f":"new-pu-elements-for-this-competition.pdf","t":"New PU elements for this Competition","n":11,"p":"24.05.24 13:35"},{"f":"infringement-car-77-pit-lane-speeding.pdf","t":"Infringement - Car 77 - Pit Lane Speeding","n":12,"p":"24.05.24 14:17"},{"f":"p1-classification.pdf","t":"P1 Classification","n":13,"p":"24.05.24 14:52"},{"f":"race-directors-event-notes-v2.pdf","t":"Race Director's Event Notes V2","n":14,"p":"24.05.24 14:57"},{"f":"infringement-car-18-pit-lane-speeding.pdf","t":"Infringement - Car 18 - Pit Lane Speeding","n":15,"p":"24.05.24 15:28"},{"f":"p2-classification.pdf","t":"P2 Classification","n":16,"p":"24.05.24 18:15"},{"f":"race-directors-note-sc2-sc1-time.pdf","t":"Race Director\u00b4s Note - SC2-SC1 Time","n":17,"p":"24.05.24 18:24"},{"f":"p1-and-p2-scrutineering.pdf","t":"P1 and P2 Scrutineering","n":18,"p":"24.05.24 19:48"},{"f":"post-qualifying-procedure.pdf","t":"Post-Qualifying Procedure","n":19,"p":"25.05.24 08:59"},{"f":"summons-car-4-incident-with-car-63.pdf","t":"Summons - Car 4 - Incident with Car 63","n":20,"p":"25.05.24 13:43"},{"f":"summons-car-63-incident-with-car-4.pdf","t":"Summons - Car 63 - Incident with Car 4","n":21,"p":"25.05.24 13:46"},{"f":"summons-car-1-alleged-driving-unnecessarily-slowly.pdf","t":"Summons - Car 1 - Alleged driving unnecessarily slowly","n":22,"p":"25.05.24 13:52"},{"f":"p3-classification.pdf","t":"P3 Classification","n":23,"p":"25.05.24 13:55"},{"f":"infringement-car-4-incident-with-car-63.pdf","t":"Infringement - Car 4 - Incident with Car 63","n":24,"p":"25.05.24 15:13"},{"f":"infringement-car-1-driving-unnecessarily-slowly.pdf","t":"Infringement - Car 1 - Driving unnecessarily slowly","n":25,"p":"25.05.24 15:23"},{"f":"summons-car-27-alleged-impeding-of-car-31.pdf","t":"Summons - Car 27 - Alleged Impeding of Car 31","n":26,"p":"25.05.24 16:59"},{"f":"summons-car-55-alleged-impeding-of-car-23.pdf","t":"Summons - Car 55 - Alleged Impeding of Car 23","n":27,"p":"25.05.24 17:01"},{"f":"summons-car-23-alleged-impeding-by-car-55.pdf","t":"Summons - Car 23 - Alleged Impeding by Car 55","n":28,"p":"25.05.24 17:02"},{"f":"summons-car-31-alleged-impeding-by-car-27.pdf","t":"Summons - Car 31 - Alleged Impeding by Car 27","n":29,"p":"25.05.24 17:18"},{"f":"provisional-qualifying-classification.pdf","t":"Provisional Qualifying Classification","n":30,"p":"25.05.24 17:23"},{"f":"qualifying-deleted-lap-times.pdf","t":"Qualifying Deleted Lap Times","n":31,"p":"25.05.24 17:29"},{"f":"qualifying-sc2-sc1-times.pdf","t":"Qualifying SC2-SC1 Times","n":32,"p":"25.05.24 17:31"},{"f":"drs-car-numbers-20-and-27.pdf","t":"DRS Car Numbers 20 and 27","n":33,"p":"25.05.24 18:47"},{"f":"summons-haas-alleged-technical-non-compliance-rear-wings.pdf","t":"Summons - Haas - Alleged technical non-compliance (Rear wings)","n":34,"p":"25.05.24 19:21"},{"f":"decision-car-55-alleged-impeding-of-car-23.pdf","t":"Decision - Car 55 - Alleged impeding of Car 23","n":35,"p":"25.05.24 19:49"},{"f":"decision-car-27-alleged-impeding-of-car-31.pdf","t":"Decision - Car 27 - Alleged impeding of Car 31","n":36,"p":"25.05.24 20:04"},{"f":"infringement-car-20-technical-non-compliance.pdf","t":"Infringement - Car 20 - Technical non-compliance","n":37,"p":"25.05.24 20:24"},{"f":"infringement-car-27-technical-non-compliance.pdf","t":"Infringement - Car 27 - Technical non-compliance","n":38,"p":"25.05.24 20:24"},{"f":"p3-and-qualifying-scrutineering.pdf","t":"P3 and Qualifying Scrutineering","n":39,"p":"25.05.24 20:29"},{"f":"decision-car-20-failing-to-set-a-lap-time-in-qualifying.pdf","t":"Decision - Car 20 - Failing to set a lap time in Qualifying","n":40,"p":"25.05.24 20:31"},{"f":"decision-car-27-failing-to-set-a-lap-time-in-qualifying.pdf","t":"Decision - Car 27 - Failing to set a lap time in Qualifying","n":41,"p":"25.05.24 20:32"},{"f":"final-qualifying-classification.pdf","t":"Final Qualifying Classification","n":42,"p":"25.05.24 20:40"},{"f":"provisional-starting-grid.pdf","t":"Provisional Starting Grid","n":43,"p":"25.05.24 20:55"},{"f":"pre-race-procedure.pdf","t":"Pre-Race Procedure","n":44,"p":"26.05.24 11:28"},{"f":"post-race-procedure.pdf","t":"Post-Race Procedure","n":45,"p":"26.05.24 11:29"},{"f":"parts-and-parameters-been-replaced-and-or-changed-during-parc-ferm\u00e9.pdf","t":"Parts and parameters been replaced and or changed during Parc Ferm\u00e9","n":46,"p":"26.05.24 12:55"},{"f":"final-starting-grid.pdf","t":"Final Starting Grid","n":47,"p":"26.05.24 13:00"},{"f":"infringement-car-31-causing-a-collision.pdf","t":"Infringement - Car 31 - Causing a collision","n":48,"p":"26.05.24 16:27"},{"f":"race-deleted-lap-times.pdf","t":"Race Deleted Lap Times","n":49,"p":"26.05.24 17:35"},{"f":"provisional-race-classification.pdf","t":"Provisional Race Classification","n":50,"p":"26.05.24 17:46"},{"f":"race-scrutineering.pdf","t":"Race Scrutineering","n":51,"p":"26.05.24 19:41"},{"f":"final-race-classification.pdf","t":"Final Race Classification","n":52,"p":"26.05.24 19:42"},{"f":"championship-points.pdf","t":"Championship Points","n":53,"p":"26.05.24 19:45"}]