[{"f":"documents\\2023\\s\u00e3o-paulo-grand-prix\\transcripts\\friday.md","t":"Friday Press Conference Transcript","n":1},{"f":"documents\\2023\\s\u00e3o-paulo-grand-prix\\event-notes-pirelli-preview.pdf","t":"Event Notes - Pirelli Preview","n":1,"p":"01.11.23 16:30"},{"f":"documents\\2023\\s\u00e3o-paulo-grand-prix\\transcripts\\sunday.md","t":"Sunday Press Conference Transcript","n":2},{"f":"documents\\2023\\s\u00e3o-paulo-grand-prix\\event-notes-circuit-map-pit-lane-drawing-and-red-zone.pdf","t":"Event Notes - Circuit Map, Pit Lane Drawing and Red Zone","n":2,"p":"02.11.23 16:26"},{"f":"documents\\2023\\s\u00e3o-paulo-grand-prix\\transcripts\\thursday.md","t":"Thursday Press Conference Transcript","n":3},{"f":"documents\\2023\\s\u00e3o-paulo-grand-prix\\car-display-procedure.pdf","t":"Car Display Procedure","n":3,"p":"02.11.23 16:31"},{"f":"documents\\2023\\s\u00e3o-paulo-grand-prix\\race-directors-event-notes.pdf","t":"Race Director's Event Notes","n":4,"p":"02.11.23 17:41"},{"f":"documents\\2023\\s\u00e3o-paulo-grand-prix\\post-race-checks-on-car-27-mexico-city-gp.pdf","t":"Post-Race Checks on Car 27, Mexico City GP","n":5,"p":"02.11.23 19:33"},{"f":"documents\\2023\\s\u00e3o-paulo-grand-prix\\pu-elements-used-per-driver-up-to-now.pdf","t":"PU elements used per driver up to now","n":6,"p":"03.11.23 12:23"},{"f":"documents\\2023\\s\u00e3o-paulo-grand-prix\\rncs-used-per-driver-up-to-now.pdf","t":"RNCs used per driver up to now","n":7,"p":"03.11.23 12:23"},{"f":"documents\\2023\\s\u00e3o-paulo-grand-prix\\post-qualifying-procedure.pdf","t":"Post-Qualifying Procedure","n":8,"p":"03.11.23 13:16"},{"f":"documents\\2023\\s\u00e3o-paulo-grand-prix\\self-scrutineering.pdf","t":"Self scrutineering","n":9,"p":"03.11.23 13:30"},{"f":"documents\\2023\\s\u00e3o-paulo-grand-prix\\entry-list.pdf","t":"Entry List","n":10,"p":"03.11.23 13:35"},{"f":"documents\\2023\\s\u00e3o-paulo-grand-prix\\new-pu-elements-for-this-competition.pdf","t":"New PU elements for this Competition","n":11,"p":"03.11.23 15:49"},{"f":"documents\\2023\\s\u00e3o-paulo-grand-prix\\curfew.pdf","t":"Curfew","n":12,"p":"03.11.23 15:50"},{"f":"documents\\2023\\s\u00e3o-paulo-grand-prix\\summons-car-27-alleged-contact-with-car-4.pdf","t":"Summons - Car 27 - Alleged contact with Car 4","n":13,"p":"03.11.23 16:30"},{"f":"documents\\2023\\s\u00e3o-paulo-grand-prix\\summons-car-4-alleged-contact-with-car-27.pdf","t":"Summons - Car 4 - Alleged contact with Car 27","n":14,"p":"03.11.23 16:35"},{"f":"documents\\2023\\s\u00e3o-paulo-grand-prix\\p1-classification.pdf","t":"P1 Classification","n":15,"p":"03.11.23 16:47"},{"f":"documents\\2023\\s\u00e3o-paulo-grand-prix\\entry-list-corrected.pdf","t":"Entry List - Corrected","n":16,"p":"03.11.23 17:05"},{"f":"documents\\2023\\s\u00e3o-paulo-grand-prix\\summons-car-4-alleged-contact-with-car-27-corrected.pdf","t":"Summons - Car 4 - Alleged contact with Car 27 - Corrected","n":17,"p":"03.11.23 17:08"},{"f":"documents\\2023\\s\u00e3o-paulo-grand-prix\\summons-car-27-alleged-contact-with-car-4-corrected.pdf","t":"Summons - Car 27 - Alleged contact with Car 4 - Corrected","n":18,"p":"03.11.23 17:14"},{"f":"documents\\2023\\s\u00e3o-paulo-grand-prix\\p1-classification-corrected.pdf","t":"P1 Classification - Corrected","n":19,"p":"03.11.23 17:21"},{"f":"documents\\2023\\s\u00e3o-paulo-grand-prix\\race-directors-note-sc2-sc1-time.pdf","t":"Race Director's Note - SC2-SC1 Time","n":20,"p":"03.11.23 17:35"},{"f":"documents\\2023\\s\u00e3o-paulo-grand-prix\\decision-car-4-alleged-contact-with-car-27.pdf","t":"Decision - Car 4 - Alleged contact with Car 27","n":21,"p":"03.11.23 18:20"},{"f":"documents\\2023\\s\u00e3o-paulo-grand-prix\\decision-car-27-alleged-contact-with-car-4.pdf","t":"Decision - Car 27 - Alleged contact with Car 4","n":22,"p":"03.11.23 18:29"},{"f":"documents\\2023\\s\u00e3o-paulo-grand-prix\\summons-car-10-alleged-impeding-at-pit-exit-by-car-63.pdf","t":"Summons - Car 10 - Alleged Impeding at Pit Exit by Car 63","n":23,"p":"03.11.23 20:14"},{"f":"documents\\2023\\s\u00e3o-paulo-grand-prix\\summons-car-31-alleged-impeding-at-pit-exit.pdf","t":"Summons - Car 31 - Alleged Impeding at Pit Exit","n":24,"p":"03.11.23 20:23"},{"f":"documents\\2023\\s\u00e3o-paulo-grand-prix\\summons-car-10-alleged-impeding-at-pit-exit.pdf","t":"Summons - Car 10 - Alleged Impeding at Pit Exit","n":25,"p":"03.11.23 20:24"},{"f":"documents\\2023\\s\u00e3o-paulo-grand-prix\\summons-car-11-alleged-impeding-at-pit-exit-by-cars.pdf","t":"Summons - Car 11 - Alleged Impeding at Pit Exit by cars","n":26,"p":"03.11.23 20:25"},{"f":"documents\\2023\\s\u00e3o-paulo-grand-prix\\provisional-qualifying-classification.pdf","t":"Provisional Qualifying Classification","n":27,"p":"03.11.23 20:29"},{"f":"documents\\2023\\s\u00e3o-paulo-grand-prix\\summons-car-63-alleged-impeding-at-pit-exit.pdf","t":"Summons - Car 63 - Alleged Impeding at Pit Exit","n":28,"p":"03.11.23 20:32"},{"f":"documents\\2023\\s\u00e3o-paulo-grand-prix\\f1-drivers-meeting.pdf","t":"F1 Drivers' Meeting","n":29,"p":"03.11.23 20:45"},{"f":"documents\\2023\\s\u00e3o-paulo-grand-prix\\decision-qualifying-sc2-sc1-times.pdf","t":"Decision - Qualifying SC2-SC1 Times","n":30,"p":"03.11.23 22:11"},{"f":"documents\\2023\\s\u00e3o-paulo-grand-prix\\p1-and-qualifying-scrutineering.pdf","t":"P1 and Qualifying scrutineering","n":31,"p":"03.11.23 22:23"},{"f":"documents\\2023\\s\u00e3o-paulo-grand-prix\\infringement-car-63-impeding-at-pit-exit.pdf","t":"Infringement - Car 63 - Impeding at Pit Exit","n":32,"p":"03.11.23 22:55"},{"f":"documents\\2023\\s\u00e3o-paulo-grand-prix\\infringement-car-10-impeding-at-pit-exit.pdf","t":"Infringement - Car 10 - Impeding at Pit Exit","n":33,"p":"03.11.23 23:27"},{"f":"documents\\2023\\s\u00e3o-paulo-grand-prix\\infringement-car-31-impeding-at-pit-exit.pdf","t":"Infringement - Car 31 - Impeding at Pit Exit","n":34,"p":"03.11.23 23:27"},{"f":"documents\\2023\\s\u00e3o-paulo-grand-prix\\final-qualifying-classification.pdf","t":"Final Qualifying Classification","n":35,"p":"03.11.23 23:35"},{"f":"documents\\2023\\s\u00e3o-paulo-grand-prix\\provisional-starting-grid.pdf","t":"Provisional Starting Grid","n":36,"p":"03.11.23 23:50"},{"f":"documents\\2023\\s\u00e3o-paulo-grand-prix\\post-sprint-shootout-procedure.pdf","t":"Post-Sprint Shootout Procedure","n":37,"p":"04.11.23 11:46"},{"f":"documents\\2023\\s\u00e3o-paulo-grand-prix\\post-sprint-procedure.pdf","t":"Post-Sprint Procedure","n":38,"p":"04.11.23 11:51"},{"f":"documents\\2023\\s\u00e3o-paulo-grand-prix\\summons-car-14-alleged-contact-with-car-31.pdf","t":"Summons - Car 14 - Alleged contact with Car 31","n":39,"p":"04.11.23 15:59"},{"f":"documents\\2023\\s\u00e3o-paulo-grand-prix\\summons-car-22-alleged-failure-to-follow-race-directors-instructions.pdf","t":"Summons - Car 22 - Alleged failure to follow Race Director's instructions","n":40,"p":"04.11.23 16:12"},{"f":"documents\\2023\\s\u00e3o-paulo-grand-prix\\summons-car-4-alleged-failure-to-follow-race-directors-instructions.pdf","t":"Summons - Car 4 - Alleged failure to follow Race Director's instructions","n":41,"p":"04.11.23 16:14"},{"f":"documents\\2023\\s\u00e3o-paulo-grand-prix\\summons-car-31-alleged-contact-with-car-14.pdf","t":"Summons - Car 31 - Alleged contact with Car 14","n":42,"p":"04.11.23 16:16"},{"f":"documents\\2023\\s\u00e3o-paulo-grand-prix\\provisional-sprint-shootout-classification.pdf","t":"Provisional Sprint Shootout Classification","n":43,"p":"04.11.23 16:25"},{"f":"documents\\2023\\s\u00e3o-paulo-grand-prix\\shootout-scrutineering.pdf","t":"ShootOut scrutineering","n":44,"p":"04.11.23 17:46"},{"f":"documents\\2023\\s\u00e3o-paulo-grand-prix\\final-sprint-shootout-classification.pdf","t":"Final Sprint Shootout Classification","n":45,"p":"04.11.23 17:50"},{"f":"documents\\2023\\s\u00e3o-paulo-grand-prix\\provisional-sprint-starting-grid.pdf","t":"Provisional Sprint Starting Grid","n":46,"p":"04.11.23 17:55"},{"f":"documents\\2023\\s\u00e3o-paulo-grand-prix\\decision-alleged-contact-with-car-14.pdf","t":"Decision - Alleged contact with Car 14","n":47,"p":"04.11.23 18:39"},{"f":"documents\\2023\\s\u00e3o-paulo-grand-prix\\decision-sprint-shootout-sc2-sc1-times.pdf","t":"Decision - Sprint Shootout SC2-SC1 Times","n":48,"p":"04.11.23 18:43"},{"f":"documents\\2023\\s\u00e3o-paulo-grand-prix\\infringement-car-22-failure-to-follow-race-directors-instructions.pdf","t":"Infringement - Car 22 - Failure to follow Race Director's instructions","n":49,"p":"04.11.23 18:49"},{"f":"documents\\2023\\s\u00e3o-paulo-grand-prix\\final-sprint-starting-grid.pdf","t":"Final Sprint Starting Grid","n":50,"p":"04.11.23 18:50"},{"f":"documents\\2023\\s\u00e3o-paulo-grand-prix\\infringement-car-4-failure-to-follow-race-directors-instructions.pdf","t":"Infringement - Car 4 - Failure to follow Race Director's instructions","n":51,"p":"04.11.23 18:56"},{"f":"documents\\2023\\s\u00e3o-paulo-grand-prix\\post-sprint-covers-on-time.pdf","t":"Post-Sprint Covers On Time","n":52,"p":"04.11.23 20:09"},{"f":"documents\\2023\\s\u00e3o-paulo-grand-prix\\provisional-sprint-classification.pdf","t":"Provisional Sprint Classification","n":53,"p":"04.11.23 20:21"},{"f":"documents\\2023\\s\u00e3o-paulo-grand-prix\\sprint-deleted-lap-times.pdf","t":"Sprint Deleted Lap Times","n":54,"p":"04.11.23 20:25"},{"f":"documents\\2023\\s\u00e3o-paulo-grand-prix\\sprint-scrutineering.pdf","t":"Sprint scrutineering","n":55,"p":"04.11.23 22:50"},{"f":"documents\\2023\\s\u00e3o-paulo-grand-prix\\final-sprint-classification.pdf","t":"Final Sprint Classification","n":56,"p":"04.11.23 22:55"},{"f":"documents\\2023\\s\u00e3o-paulo-grand-prix\\championship-points-after-sprint.pdf","t":"Championship Points after Sprint","n":57,"p":"04.11.23 23:00"},{"f":"documents\\2023\\s\u00e3o-paulo-grand-prix\\pre-race-procedure.pdf","t":"Pre-Race Procedure","n":58,"p":"05.11.23 14:11"},{"f":"documents\\2023\\s\u00e3o-paulo-grand-prix\\post-race-procedure.pdf","t":"Post-Race Procedure","n":59,"p":"05.11.23 14:16"},{"f":"documents\\2023\\s\u00e3o-paulo-grand-prix\\parts-and-parameters-been-replaced-and-or-changed-during-parc-ferm\u00e9.pdf","t":"Parts and parameters been replaced and or changed during Parc Ferm\u00e9","n":60,"p":"05.11.23 15:55"},{"f":"documents\\2023\\s\u00e3o-paulo-grand-prix\\final-starting-grid.pdf","t":"Final Starting Grid","n":61,"p":"05.11.23 16:00"},{"f":"documents\\2023\\s\u00e3o-paulo-grand-prix\\provisional-race-classification.pdf","t":"Provisional Race Classification","n":62,"p":"05.11.23 20:20"},{"f":"documents\\2023\\s\u00e3o-paulo-grand-prix\\summons-s\u00e3o-paulo-f1-organisation.pdf","t":"Summons - S\u00e3o Paulo F1 Organisation","n":63,"p":"05.11.23 21:00"},{"f":"documents\\2023\\s\u00e3o-paulo-grand-prix\\race-scrutineering.pdf","t":"Race scrutineering","n":64,"p":"05.11.23 22:06"},{"f":"documents\\2023\\s\u00e3o-paulo-grand-prix\\decision-s\u00e3o-paulo-f1-organisation.pdf","t":"Decision - S\u00e3o Paulo F1 Organisation","n":65,"p":"05.11.23 22:25"},{"f":"documents\\2023\\s\u00e3o-paulo-grand-prix\\final-race-classification.pdf","t":"Final Race Classification","n":66,"p":"05.11.23 22:30"},{"f":"documents\\2023\\s\u00e3o-paulo-grand-prix\\championship-points.pdf","t":"Championship Points","n":67,"p":"05.11.23 22:35"}]